LICENSE
MANIFEST.in
README.rst
VENDOR-LICENSES.md
setup.cfg
setup.py
tox.ini
doc/Makefile
doc/changelog.rst
doc/changes.rst
doc/conf.py
doc/index.rst
doc/make.bat
doc/shoop-changelog.rst
doc/web_api.rst
doc/_ext/django_sphinx.py
doc/_ext/djangodocs.py
doc/_ext/djangodocs.py.LICENSE
doc/_ext/shuup_introspection_helper.py
doc/_theme/sphinx_shoop_theme/__init__.py
doc/api/modules.rst
doc/api/shuup.addons.admin_module.rst
doc/api/shuup.addons.admin_module.views.rst
doc/api/shuup.addons.rst
doc/api/shuup.admin.breadcrumbs.rst
doc/api/shuup.admin.dashboard.rst
doc/api/shuup.admin.forms.rst
doc/api/shuup.admin.modules.attributes.rst
doc/api/shuup.admin.modules.attributes.views.rst
doc/api/shuup.admin.modules.categories.rst
doc/api/shuup.admin.modules.categories.views.rst
doc/api/shuup.admin.modules.contact_groups.rst
doc/api/shuup.admin.modules.contact_groups.views.rst
doc/api/shuup.admin.modules.contacts.rst
doc/api/shuup.admin.modules.contacts.views.rst
doc/api/shuup.admin.modules.content.rst
doc/api/shuup.admin.modules.currencies.rst
doc/api/shuup.admin.modules.currencies.views.rst
doc/api/shuup.admin.modules.customers_dashboard.rst
doc/api/shuup.admin.modules.demo.rst
doc/api/shuup.admin.modules.manufacturers.rst
doc/api/shuup.admin.modules.manufacturers.views.rst
doc/api/shuup.admin.modules.media.rst
doc/api/shuup.admin.modules.orders.rst
doc/api/shuup.admin.modules.orders.views.rst
doc/api/shuup.admin.modules.permission_groups.rst
doc/api/shuup.admin.modules.permission_groups.views.rst
doc/api/shuup.admin.modules.product_types.rst
doc/api/shuup.admin.modules.product_types.views.rst
doc/api/shuup.admin.modules.products.forms.rst
doc/api/shuup.admin.modules.products.rst
doc/api/shuup.admin.modules.products.views.rst
doc/api/shuup.admin.modules.rst
doc/api/shuup.admin.modules.sales_dashboard.rst
doc/api/shuup.admin.modules.sales_units.rst
doc/api/shuup.admin.modules.sales_units.views.rst
doc/api/shuup.admin.modules.sample_data.rst
shuup.egg-info/PKG-INFO
shuup.egg-info/SOURCES.txt
shuup.egg-info/dependency_links.txt
shuup.egg-info/requires.txt
shuup.egg-info/top_level.txt
