Metadata-Version: 1.1
Name: shuup
Version: 1.6.0
Summary: E-Commerce Platform
Home-page: http://shuup.com/
Author: Shuup Inc.
Author-email: shuup@shuup.com
License: proprietary
Download-URL: https://github.com/shuup/shuup/releases/download/v1.6.0/shuup-1.6.0-py2.py3-none-any.whl
Platform: UNKNOWN
Classifier: Development Status :: 5 - Production/Stable
Classifier: Intended Audience :: Developers
Classifier: License :: Other/Proprietary License
Classifier: Natural Language :: English
Classifier: Natural Language :: Chinese (Simplified)
Classifier: Natural Language :: Finnish
Classifier: Natural Language :: Japanese
Classifier: Natural Language :: Portuguese (Brazilian)
Classifier: Programming Language :: JavaScript
Classifier: Programming Language :: Python :: 2
Classifier: Programming Language :: Python :: 2.7
Classifier: Programming Language :: Python :: 3
Classifier: Programming Language :: Python :: 3.4
Classifier: Programming Language :: Python :: 3.5
Classifier: Programming Language :: Python :: 3.6
Classifier: Topic :: Internet :: WWW/HTTP :: Dynamic Content
Classifier: Topic :: Internet :: WWW/HTTP :: Site Management
Classifier: Topic :: Office/Business
Classifier: Topic :: Software Development :: Libraries :: Application Frameworks
Classifier: Topic :: Software Development :: Libraries :: Python Modules
